{
	"animations": [
		{
			"loop": false,
			"offsets": [
				0,
				40
			],
			"anim": "idle",
			"fps": 24,
			"name": "idle",
			"indices": []
		},
		{
			"offsets": [
				10,
				60
			],
			"loop": false,
			"fps": 24,
			"anim": "singDOWN",
			"indices": [],
			"name": "down"
		},
		{
			"offsets": [
				-34,
				51
			],
			"loop": false,
			"fps": 24,
			"anim": "singUP",
			"indices": [],
			"name": "up"
		},
		{
			"offsets": [
				-4,
				42
			],
			"loop": false,
			"fps": 24,
			"anim": "singRIGHT",
			"indices": [],
			"name": "right"
		},
		{
			"loop": false,
			"offsets": [
				-14,
				44
			],
			"anim": "singLEFT",
			"fps": 24,
			"name": "left",
			"indices": []
		}
	],
	"no_antialiasing": false,
	"image": "characters/supernovae real best character",
	"position": [
		90,
		430
	],
	"healthicon": "bambi-joke",
	"flip_x": false,
	"healthbar_colors": [
		166,
		99,
		255
	],
	"camera_position": [
		0,
		-40
	],
	"sing_duration": 6.1,
	"scale": 1
}